sa_dump_engine/__init__.py
sa_dump_engine/dump_engine.py
sa_dump_engine-0.3.0.dist-info/METADATA
sa_dump_engine-0.3.0.dist-info/WHEEL
sa_dump_engine-0.3.0.dist-info/licenses/LICENSE
sa_dump_engine-0.3.0.dist-info/RECORD
