Metadata-Version: 2.3
Name: sa-dump-engine
Version: 0.3.0
Summary: a mock engine to output SQL statements generated by SQLAlchemy
Project-URL: Repository, https://github.com/mitszo/sa-dump-engine
Author-email: Mitsumasa IMAZU <mits.imaz@gmail.com>
License: MIT License
License-File: LICENSE
Requires-Python: >=3.9
Requires-Dist: sqlalchemy>=2.0.36
